tempath/__init__.py
tempath-0.2.0.dist-info/LICENSE
tempath-0.2.0.dist-info/METADATA
tempath-0.2.0.dist-info/WHEEL
tempath-0.2.0.dist-info/top_level.txt
tempath-0.2.0.dist-info/RECORD
