Metadata-Version: 2.1
Name: tempath
Version: 0.2.0
Summary: Auto creates and removes files and folders for testing.
Home-page: http://github.com/alexpdev/tempath
Author: alexpdev
Author-email: alexpdev@protonmail.com
License: GNU LGPL v3
Project-URL: Source Code, https://github.com/alexpdev/tempath
Keywords: Unit Tests,Testing,filesystem,automation
Platform: UNKNOWN
Classifier: Programming Language :: Python :: 3.0
Classifier: Programming Language :: Python :: 3.1
Classifier: Programming Language :: Python :: 3.2
Classifier: Programming Language :: Python :: 3.3
Classifier: Programming Language :: Python :: 3.4
Classifier: Programming Language :: Python :: 3.5
Classifier: Programming Language :: Python :: 3.6
Classifier: Programming Language :: Python :: 3.7
Classifier: Programming Language :: Python :: 3.8
Classifier: Programming Language :: Python :: 3.9
Classifier: Programming Language :: Python :: 3.10
Classifier: Development Status :: 3 - Alpha
Classifier: Operating System :: OS Independent
Classifier: Programming Language :: Python :: 3
Classifier: Topic :: Software Development :: Libraries :: Python Modules
Classifier: License :: OSI Approved :: GNU Lesser General Public License v3 or later (LGPLv3+)
License-File: LICENSE
